pytest_drill_sergeant/__init__.py
pytest_drill_sergeant/config.py
pytest_drill_sergeant/models.py
pytest_drill_sergeant/plugin.py
pytest_drill_sergeant/py.typed
pytest_drill_sergeant/pytest_options.py
pytest_drill_sergeant/utils/__init__.py
pytest_drill_sergeant/utils/helpers.py
pytest_drill_sergeant/validators/__init__.py
pytest_drill_sergeant/validators/aaa.py
pytest_drill_sergeant/validators/base.py
pytest_drill_sergeant/validators/error_reporter.py
pytest_drill_sergeant/validators/file_length.py
pytest_drill_sergeant/validators/marker.py
pytest_drill_sergeant/validators/return_type.py
pytest_drill_sergeant-0.2.0.dist-info/licenses/LICENSE
pytest_drill_sergeant-0.2.0.dist-info/METADATA
pytest_drill_sergeant-0.2.0.dist-info/WHEEL
pytest_drill_sergeant-0.2.0.dist-info/entry_points.txt
pytest_drill_sergeant-0.2.0.dist-info/top_level.txt
pytest_drill_sergeant-0.2.0.dist-info/RECORD
