Metadata-Version: 2.4
Name: pytest-drill-sergeant
Version: 0.2.0
Summary: A pytest plugin that enforces test quality standards through automatic marker detection and AAA structure validation
Author-email: Jeff Richley <jeffrichley@gmail.com>
License-Expression: MIT
Project-URL: Homepage, https://github.com/jeffrichley/pytest-drill-sergeant
Project-URL: Repository, https://github.com/jeffrichley/pytest-drill-sergeant.git
Project-URL: Issues, https://github.com/jeffrichley/pytest-drill-sergeant/issues
Keywords: pytest,testing,quality,standards,AAA,markers
Classifier: Development Status :: 4 - Beta
Classifier: Framework :: Pytest
Classifier: Intended Audience :: Developers
Classifier: Operating System :: OS Independent
Classifier: Programming Language :: Python :: 3
Classifier: Programming Language :: Python :: 3.12
Classifier: Topic :: Software Development :: Testing
Requires-Python: >=3.12
License-File: LICENSE
Requires-Dist: pytest>=7.0.0
Provides-Extra: dev
Requires-Dist: pytest>=7.0.0; extra == "dev"
Requires-Dist: pytest-cov>=4.0.0; extra == "dev"
Requires-Dist: mypy>=1.0.0; extra == "dev"
Requires-Dist: ruff>=0.1.0; extra == "dev"
Requires-Dist: black>=23.0.0; extra == "dev"
Requires-Dist: pre-commit>=3.0.0; extra == "dev"
Provides-Extra: test
Requires-Dist: hypothesis>=6.136.6; extra == "test"
Requires-Dist: pytest-benchmark>=4.0.0; extra == "test"
Requires-Dist: psutil>=5.9.0; extra == "test"
Provides-Extra: docs
Requires-Dist: mkdocs>=1.5.0; extra == "docs"
Requires-Dist: mkdocs-material>=9.6.17; extra == "docs"
Requires-Dist: mkdocstrings[python]>=0.30.0; extra == "docs"
Requires-Dist: mike>=2.1.3; extra == "docs"
Requires-Dist: mkdocs-git-revision-date-localized-plugin>=1.4.7; extra == "docs"
Requires-Dist: mkdocs-mermaid2-plugin>=1.2.1; extra == "docs"
Provides-Extra: typecheck
Requires-Dist: mypy; extra == "typecheck"
Provides-Extra: security
Requires-Dist: pip-audit; extra == "security"
Dynamic: license-file
